modbus_proxy.py
modbus_proxy-0.8.0.dist-info/LICENSE
modbus_proxy-0.8.0.dist-info/METADATA
modbus_proxy-0.8.0.dist-info/WHEEL
modbus_proxy-0.8.0.dist-info/entry_points.txt
modbus_proxy-0.8.0.dist-info/top_level.txt
modbus_proxy-0.8.0.dist-info/zip-safe
modbus_proxy-0.8.0.dist-info/RECORD
