Metadata-Version: 2.1
Name: modbus-proxy
Version: 0.8.0
Summary: ModBus TCP proxy
Home-page: https://github.com/tiagocoutinho/modbus-proxy
Author: Tiago Coutinho
Author-email: coutinhotiago@gmail.com
License: GNU General Public License v3
Keywords: modbus,tcp,proxy
Classifier: Development Status :: 4 - Beta
Classifier: Intended Audience :: Developers
Classifier: Intended Audience :: Manufacturing
Classifier: Intended Audience :: Science/Research
Classifier: License :: OSI Approved :: GNU General Public License v3 (GPLv3)
Classifier: Natural Language :: English
Classifier: Programming Language :: Python :: 3
Classifier: Programming Language :: Python :: 3 :: Only
Classifier: Programming Language :: Python :: 3.9
Classifier: Programming Language :: Python :: 3.10
Classifier: Programming Language :: Python :: 3.11
Classifier: Programming Language :: Python :: 3.12
Requires-Python: >=3.9
License-File: LICENSE
Provides-Extra: test
Requires-Dist: pytest>=6; extra == "test"
Requires-Dist: pytest-cov>=2; extra == "test"
Requires-Dist: pytest-asyncio>=0.15; extra == "test"
Requires-Dist: flake8>=3.9; extra == "test"
Requires-Dist: tox>=3.24; extra == "test"
Provides-Extra: toml
Requires-Dist: toml; extra == "toml"
Provides-Extra: yaml
Requires-Dist: PyYAML; extra == "yaml"
